fortran_format_converter/__init__.py
fortran_format_converter/_converter.py
fortran_format_converter/py.typed
fortran_format_converter-0.1.3.dist-info/LICENSE
fortran_format_converter-0.1.3.dist-info/METADATA
fortran_format_converter-0.1.3.dist-info/WHEEL
fortran_format_converter-0.1.3.dist-info/top_level.txt
fortran_format_converter-0.1.3.dist-info/RECORD
