Metadata-Version: 2.1
Name: fortran-format-converter
Version: 0.1.3
Summary: Convert Fortran format specifiers to Python format strings.
Home-page: https://github.com/ccarocean/fortran-format-converter
Author: Michael R. Shannon
Author-email: mrshannon.aerospace@gmail.com
License: MIT
Platform: UNKNOWN
Classifier: Development Status :: 4 - Beta
Classifier: Intended Audience :: Science/Research
Classifier: License :: OSI Approved :: MIT License
Classifier: Programming Language :: Python
Classifier: Programming Language :: Python :: 3
Classifier: Programming Language :: Python :: 3.5
Classifier: Programming Language :: Python :: 3.6
Classifier: Programming Language :: Python :: 3.7
Classifier: Topic :: Scientific/Engineering
Requires-Dist: cached-property
Requires-Dist: regex
